{
  "$schema": "https://ui.shadcn.com/schema/registry.json",
  "name": "hata-ui",
  "homepage": "https://github.com/hatv009/hata-ui",
  "include": ["docs/agent/registry.json"],
  "items": [
    {
      "name": "project-conventions",
      "type": "registry:item",
      "title": "Project Conventions",
      "description": "Shared project conventions, editor settings and agent instructions.",
      "files": [
        {
          "path": "AGENTS.md",
          "type": "registry:file",
          "target": "~/AGENTS.md"
        },
        {
          "path": "docs/README.md",
          "type": "registry:file",
          "target": "~/docs/README.md"
        }
      ]
    }
  ]
}